w3ai_sdk/__init__.py
w3ai_sdk/const.py
w3ai_sdk/core.py
w3ai_sdk-0.0.7.dist-info/LICENSE.txt
w3ai_sdk-0.0.7.dist-info/METADATA
w3ai_sdk-0.0.7.dist-info/WHEEL
w3ai_sdk-0.0.7.dist-info/top_level.txt
w3ai_sdk-0.0.7.dist-info/RECORD
