Metadata-Version: 2.1
Name: w3ai-sdk
Version: 0.0.7
Summary: W3AI Flatform API
Home-page: https://github.com/yourname/yourproject
Author: AIOZ-AITeam
Author-email: tu.chau.phan@aioz.io
License: UNKNOWN
Platform: UNKNOWN
License-File: LICENSE.txt
Requires-Dist: web3
